LICENSE
MANIFEST.in
README.md
setup.cfg
setup.py
poc/__init__.py
poc/aio_server.py
poc/aio_server_start_stop.py
poc/client.task.result.test.py
poc/client.task.test.py
poc/client.test.py
poc/client_apps.py
poc/decorator.py
poc/del.py
poc/distributed_promise.py
poc/event.py
poc/exec_code.py
poc/mixin.py
poc/outgoing_channel.py
poc/process_test.py
poc/random_nodes_gen.py
poc/subprocess_poc.py
poc/test-process.py
troup/__init__.py
troup/__main__.py
troup/apps.py
troup/client.py
troup/command.py
troup/debug.py
troup/distributed.py
troup/infrastructure.py
troup/main.py
troup/messaging.py
troup/metadata.py
troup/node.py
troup/observer.py
troup/process.py
troup/setup.py
troup/store.py
troup/system.py
troup/tasks.py
troup/testtools.py
troup/threading.py
troup.egg-info/PKG-INFO
troup.egg-info/SOURCES.txt
troup.egg-info/dependency_links.txt
troup.egg-info/entry_points.txt
troup.egg-info/requires.txt
troup.egg-info/top_level.txt