Metadata-Version: 1.1
Name: troup
Version: 0.1.2
Summary: Troup system
Home-page: https://github.com/troup-system/troup
Author: Pavle Jonoski
Author-email: jonoski.pavle@gmail.com
License: http://www.apache.org/licenses/LICENSE-2.0
Keywords: development distributed computing
Platform: UNKNOWN
Classifier: Development Status :: 2 - Pre-Alpha
Classifier: Intended Audience :: Developers
Classifier: Topic :: System :: Distributed Computing
Classifier: Topic :: Utilities
Classifier: License :: OSI Approved :: Apache Software License
Classifier: Programming Language :: Python :: 3
Classifier: Programming Language :: Python :: 3.4
Classifier: Programming Language :: Python :: 3.5
